setup.cfg
setup.py
pyeq2/DEDICATION.txt
pyeq2/IModel.py
pyeq2/LICENSE.txt
pyeq2/Model_2D_BaseClass.py
pyeq2/Model_3D_BaseClass.py
pyeq2/PolyFunctions.py
pyeq2/README.txt
pyeq2/__init__.py
pyeq2.egg-info/PKG-INFO
pyeq2.egg-info/SOURCES.txt
pyeq2.egg-info/dependency_links.txt
pyeq2.egg-info/top_level.txt
pyeq2/DataCache/DataCache.py
pyeq2/DataCache/DataCacheFunctions.py
pyeq2/DataCache/__init__.py
pyeq2/ExtendedVersionHandlers/ExtendedVersionHandler_Default.py
pyeq2/ExtendedVersionHandlers/ExtendedVersionHandler_ExponentialDecay.py
pyeq2/ExtendedVersionHandlers/ExtendedVersionHandler_ExponentialDecayAndOffset.py
pyeq2/ExtendedVersionHandlers/ExtendedVersionHandler_ExponentialGrowth.py
pyeq2/ExtendedVersionHandlers/ExtendedVersionHandler_ExponentialGrowthAndOffset.py
pyeq2/ExtendedVersionHandlers/ExtendedVersionHandler_Inverse.py
pyeq2/ExtendedVersionHandlers/ExtendedVersionHandler_InverseWithOffset.py
pyeq2/ExtendedVersionHandlers/ExtendedVersionHandler_LinearDecay.py
pyeq2/ExtendedVersionHandlers/ExtendedVersionHandler_LinearDecayAndOffset.py
pyeq2/ExtendedVersionHandlers/ExtendedVersionHandler_LinearGrowth.py
pyeq2/ExtendedVersionHandlers/ExtendedVersionHandler_LinearGrowthAndOffset.py
pyeq2/ExtendedVersionHandlers/ExtendedVersionHandler_Offset.py
pyeq2/ExtendedVersionHandlers/ExtendedVersionHandler_Reciprocal.py
pyeq2/ExtendedVersionHandlers/ExtendedVersionHandler_ReciprocalWithOffset.py
pyeq2/ExtendedVersionHandlers/IExtendedVersionHandler.py
pyeq2/ExtendedVersionHandlers/__init__.py
pyeq2/Models_2D/Astrophysics.py
pyeq2/Models_2D/BioScience.py
pyeq2/Models_2D/BurkardtCollectionBased.py
pyeq2/Models_2D/Engineering.py
pyeq2/Models_2D/Exponential.py
pyeq2/Models_2D/FourierSeries.py
pyeq2/Models_2D/LegendrePolynomial.py
pyeq2/Models_2D/Logarithmic.py
pyeq2/Models_2D/Miscellaneous.py
pyeq2/Models_2D/NIST.py
pyeq2/Models_2D/Optical.py
pyeq2/Models_2D/Peak.py
pyeq2/Models_2D/Polyfunctional.py
pyeq2/Models_2D/Polynomial.py
pyeq2/Models_2D/Power.py
pyeq2/Models_2D/Rational.py
pyeq2/Models_2D/Sigmoidal.py
pyeq2/Models_2D/Simple.py
pyeq2/Models_2D/Spline.py
