Metadata-Version: 1.1
Name: pyeq2
Version: 12.2.7
Summary: Large curve fitting and surface fitting library with hundreds of named equations
Home-page: https://bitbucket.org/zunzuncode/pyeq2
Author: James Phillips
Author-email: zunzun@zunzun.com
License: BSD
Keywords: curve fitting and surface fitting
Platform: UNKNOWN
Classifier: Development Status :: 6 - Mature
Classifier: Intended Audience :: Developers
Classifier: Topic :: Scientific/Engineering :: Mathematics
Classifier: License :: OSI Approved :: BSD License
Classifier: Programming Language :: Python :: 2
